{
  "$schema": "https://biomejs.dev/schemas/2.3.12/schema.json",
  "root": false,
  "extends": "//",
  "linter": {
    "rules": {
      "a11y": {
        "noAccessKey": "error",
        "noAriaHiddenOnFocusable": "error",
        "noAriaUnsupportedElements": "error",
        "noAutofocus": "error",
        "noDistractingElements": "error",
        "noHeaderScope": "error",
        "noInteractiveElementToNoninteractiveRole": "error",
        "noLabelWithoutControl": "error",
        "noNoninteractiveElementToInteractiveRole": "error",
        "noNoninteractiveTabindex": "error",
        "noPositiveTabindex": "error",
        "noRedundantAlt": "error",
        "noRedundantRoles": "error",
        "noSvgWithoutTitle": "error",
        "useAltText": "error",
        "useAnchorContent": "error",
        "useAriaActivedescendantWithTabindex": "error",
        "useAriaPropsForRole": "error",
        "useButtonType": "error",
        "useFocusableInteractive": "error",
        "useGenericFontNames": "error",
        "useHeadingContent": "error",
        "useHtmlLang": "error",
        "useIframeTitle": "error",
        "useKeyWithClickEvents": "error",
        "useKeyWithMouseEvents": "error",
        "useMediaCaption": "error",
        "useSemanticElements": "error",
        "useValidAnchor": "error",
        "useValidAriaProps": "error",
        "useValidAriaRole": "error",
        "useValidAriaValues": "error",
        "useValidLang": "error"
      },
      "complexity": {
        "noUselessFragments": "error"
      },
      "correctness": {
        "noChildrenProp": "error",
        "noVoidElementsWithChildren": "error"
      },
      "security": {
        "noBlankTarget": "error",
        "noDangerouslySetInnerHtml": "error",
        "noDangerouslySetInnerHtmlWithChildren": "error"
      },
      "style": {
        "noImplicitBoolean": "error",
        "useComponentExportOnlyModules": "error",
        "useConsistentCurlyBraces": "error",
        "useFragmentSyntax": "error"
      },
      "suspicious": {
        "noArrayIndexKey": "error",
        "noCommentText": "error",
        "noDuplicateJsxProps": "error",
        "noSuspiciousSemicolonInJsx": "error"
      }
    }
  },
  "files": {
    "includes": [
      "**",
      "!**/routeTree.gen.ts",
      "!src/locales/**"
    ]
  }
}
